{
    "os": "Linux-5.19.0-41-generic-x86_64-with-glibc2.35",
    "python": "3.10.9",
    "heartbeatAt": "2023-05-31T15:25:40.631525",
    "startedAt": "2023-05-31T15:25:39.780363",
    "docker": null,
    "cuda": null,
    "args": [
        "--project",
        "taxi",
        "--entity",
        "tensorflowq",
        "--data_artifact",
        "tensorflowq/taxi/Taxi:v0"
    ],
    "state": "running",
    "program": "/home/hilbert/zoomcamps/weights_biases/train.py",
    "codePath": "weights_biases/train.py",
    "git": {
        "remote": "https://github.com/qCircuit/zoomcamps",
        "commit": "81d239d43974cb0ac0007140a0abc1eb15e57c05"
    },
    "email": "tensorflowq@gmail.com",
    "root": "/home/hilbert/zoomcamps",
    "host": "qCircuit",
    "username": "hilbert",
    "executable": "/home/hilbert/anaconda3/bin/python",
    "cpu_count": 8,
    "cpu_count_logical": 16,
    "cpu_freq": {
        "current": 4546.8714375,
        "min": 800.0,
        "max": 5300.0
    },
    "cpu_freq_per_core": [
        {
            "current": 4535.038,
            "min": 800.0,
            "max": 5300.0
        },
        {
            "current": 4381.917,
            "min": 800.0,
            "max": 5300.0
        },
        {
            "current": 4630.626,
            "min": 800.0,
            "max": 5300.0
        },
        {
            "current": 4465.29,
            "min": 800.0,
            "max": 5300.0
        },
        {
            "current": 4713.345,
            "min": 800.0,
            "max": 5300.0
        },
        {
            "current": 4693.039,
            "min": 800.0,
            "max": 5300.0
        },
        {
            "current": 4718.534,
            "min": 800.0,
            "max": 5300.0
        },
        {
            "current": 4462.478,
            "min": 800.0,
            "max": 5300.0
        },
        {
            "current": 4542.377,
            "min": 800.0,
            "max": 5300.0
        },
        {
            "current": 3100.0,
            "min": 800.0,
            "max": 5300.0
        },
        {
            "current": 4619.481,
            "min": 800.0,
            "max": 5300.0
        },
        {
            "current": 4573.021,
            "min": 800.0,
            "max": 5300.0
        },
        {
            "current": 4425.654,
            "min": 800.0,
            "max": 5300.0
        },
        {
            "current": 4406.649,
            "min": 800.0,
            "max": 5300.0
        },
        {
            "current": 4504.586,
            "min": 800.0,
            "max": 5300.0
        },
        {
            "current": 4675.884,
            "min": 800.0,
            "max": 5300.0
        }
    ],
    "disk": {
        "total": 467.8895797729492,
        "used": 87.99822235107422
    },
    "memory": {
        "total": 31.172454833984375
    }
}
